[
  {
    "py/object": "models.Group.Group",
    "footer": "",
    "header": "",
    "id": null,
    "name": ""
  },
  {
    "py/object": "models.Group.Group",
    "footer": "footerlK \"",
    "header": "headerb ",
    "id": null,
    "name": "nameu \\yH_NR"
  },
  {
    "py/object": "models.Group.Group",
    "footer": "footeryy-K8+L",
    "header": "header1!#yn;",
    "id": null,
    "name": "name joBf,"
  },
  {
    "py/object": "models.Group.Group",
    "footer": "footer1j? k",
    "header": "headerqW B FdC",
    "id": null,
    "name": "nameWLP\""
  },
  {
    "py/object": "models.Group.Group",
    "footer": "footerP U{",
    "header": "headerLGs^",
    "id": null,
    "name": "name\"f )u2.;8"
  },
  {
    "py/object": "models.Group.Group",
    "footer": "footerOQPMr ]MP",
    "header": "header]r}Bt`",
    "id": null,
    "name": "name,#"
  }
]